<?xml version="1.0" encoding="UTF-8"?>
<!DOCTYPE mapper PUBLIC "-//mybatis.org//DTD Mapper 3.0//EN" "http://mybatis.org/dtd/mybatis-3-mapper.dtd">

<mapper namespace="com.dao.ZhandianWuzhangaiDao">

	<!-- 可根据自己的需求，是否要使用 -->
    <resultMap type="com.entity.ZhandianWuzhangaiEntity" id="zhandianWuzhangaiMap">
        <result property="id" column="id"/>
        <result property="zhandianming" column="zhandianming"/>
        <result property="jingdu" column="jingdu"/>
        <result property="weidu" column="weidu"/>
        <result property="wuzhangaijibie" column="wuzhangaijibie"/>
        <result property="shengjiangtai" column="shengjiangtai"/>
        <result property="mangdao" column="mangdao"/>
        <result property="zhuizhu" column="zhuizhu"/>
        <result property="zuoweishu" column="zuoweishu"/>
        <result property="cesuo" column="cesuo"/>
        <result property="tingchechang" column="tingchechang"/>
        <result property="beizhu" column="beizhu"/>
        <result property="addtime" column="addtime"/>
    </resultMap>

    <select id="selectListVO"
        resultType="com.entity.vo.ZhandianWuzhangaiVO" >
        SELECT * FROM zhandian_wuzhangai  zhandian_wuzhangai
        <where> 1=1 ${ew.sqlSegment}</where>
    </select>

    <select id="selectVO"
        resultType="com.entity.vo.ZhandianWuzhangaiVO" >
        SELECT  zhandian_wuzhangai.* FROM zhandian_wuzhangai  zhandian_wuzhangai
         <where> 1=1 ${ew.sqlSegment}</where>
    </select>

    <select id="selectListView"
        resultType="com.entity.view.ZhandianWuzhangaiView" >
        SELECT  zhandian_wuzhangai.* FROM zhandian_wuzhangai  zhandian_wuzhangai
        <where> 1=1 ${ew.sqlSegment}</where>
    </select>

    <select id="selectView"
        resultType="com.entity.view.ZhandianWuzhangaiView" >
        SELECT * FROM zhandian_wuzhangai  zhandian_wuzhangai <where> 1=1 ${ew.sqlSegment}</where>
    </select>

    <select id="selectListView"
        resultType="com.entity.view.ZhandianWuzhangaiView">
        SELECT  zhandian_wuzhangai.* FROM zhandian_wuzhangai  zhandian_wuzhangai
        <where> 1=1 ${ew.sqlSegment}</where>
    </select>

    <select id="selectByStationName" resultType="com.entity.ZhandianWuzhangaiEntity">
        SELECT * FROM zhandian_wuzhangai WHERE zhandianming = #{zhandianming} LIMIT 1
    </select>

</mapper>
